Metadata-Version: 2.1
Name: django-embed-gist
Version: 2020.7.1
Summary: embed gist
Home-page: https://github.com/andrewp-as-is/django-embed-gist.py
License: Unlicense
Keywords: django gist
Platform: UNKNOWN
Classifier: Framework :: Django
Classifier: License :: Public Domain
Classifier: Operating System :: OS Independent
Classifier: Programming Language :: Python :: 3
